dbsqlcli/__init__.py
dbsqlcli/clibuffer.py
dbsqlcli/clistyle.py
dbsqlcli/clitoolbar.py
dbsqlcli/compat.py
dbsqlcli/completer.py
dbsqlcli/completion_refresher.py
dbsqlcli/config.py
dbsqlcli/dbsqlclirc
dbsqlcli/key_bindings.py
dbsqlcli/lexer.py
dbsqlcli/main.py
dbsqlcli/packages/__init__.py
dbsqlcli/packages/completion_engine.py
dbsqlcli/packages/filepaths.py
dbsqlcli/packages/format_utils.py
dbsqlcli/packages/literals/__init__.py
dbsqlcli/packages/literals/main.py
dbsqlcli/packages/parseutils.py
dbsqlcli/packages/prompt_utils.py
dbsqlcli/packages/special/__init__.py
dbsqlcli/packages/special/dbcommands.py
dbsqlcli/packages/special/favoritequeries.py
dbsqlcli/packages/special/iocommands.py
dbsqlcli/packages/special/main.py
dbsqlcli/packages/special/utils.py
dbsqlcli/packages/tabular_output/__init__.py
dbsqlcli/packages/tabular_output/sql_format.py
dbsqlcli/sqlexecute.py
dbsqlcli-0.1.1.dist-info/entry_points.txt
dbsqlcli-0.1.1.dist-info/LICENSE.txt
dbsqlcli-0.1.1.dist-info/WHEEL
dbsqlcli-0.1.1.dist-info/METADATA
dbsqlcli-0.1.1.dist-info/RECORD
